{
 "界面": "Interfaz",
 "外观设置": "Configuración de apariencia",
 "工作环境": "Entorno de trabajo",
 "文档云同步": "Sincronización de documentos en la nube",
 "可以从自己的手机或其他电脑访问这台电脑打开过的文档": "Acceda desde su teléfono u otro equipo a los documentos abiertos en este equipo",
 "使用鼠标双击关闭标签": "Cerrar pestañas con doble clic",
 "网页浏览设置": "Configuración de navegación web",
 "打开备份中心": "Abrir centro de copias de seguridad",
 "其他": "Otros",
 "切换窗口管理模式": "Cambiar modo de gestión de ventanas",
 "切换为经典界面": "Cambiar a interfaz clásica",
 "恢复初始默认设置": "Restaurar configuración predeterminada",
 "设置中心": "Centro de configuración",
 "经典皮肤": "Temas clásicos",
 "桌面图标": "Icono del escritorio",
 "首页布局": "Disposición de la página principal",
 "首页主导航栏名称隐藏": "Ocultar nombres de la barra de navegación",
 "自定义外观": "Apariencia personalizada",
 "窗口": "Ventana",
 "背景图像和颜色": "Imagen y color de fondo",
 "背景透明度": "Transparencia del fondo",
 "窗口半透明效果": "Efecto de ventana translúcida",
 "需要系统和": "Requiere soporte del sistema",
 "硬件加速支持": "y aceleración por hardware",
 "界面字体": "Fuente de la interfaz",
 "恢复默认值": "Restaurar valores predeterminados",
 "下载": "Descargas",
 "下载目录": "Carpeta de descargas",
 "下载前询问每个文件的保存位置": "Preguntar dónde guardar cada archivo antes de descargar",
 "下载完成记录": "Registro de descargas completadas",
 "上报应用诊断信息": "Enviar información de diagnóstico",
 "上传日志或dump文件以帮助研发团队更好定位和解决问题": "Subir registros o archivos dump para ayudar al equipo a diagnosticar problemas",
 "云文档默认启用自动保存": "Activar autoguardado en documentos de la nube por defecto",
 "企业管理员已开启企业文档云同步": "El administrador corporativo activó la sincronización de documentos",
 "企业管理员已禁止企业文档云同步": "El administrador corporativo desactivó la sincronización de documentos",
 "会员特权提示": "Aviso de privilegios de membresía",
 "清除": "Borrar",
 "缓存的图像和文件": "Imágenes y archivos en caché",
 "浏览数据": "Datos de navegación",
 "确定": "Aceptar",
 "取消": "Cancelar",
 "安全性": "Seguridad",
 "已开启": "Activado",
 "已关闭": "Desactivado",
 "开启": "Activar",
 "关闭": "Cerrar",
 "设置项": "Opciones",
 "PDF预览": "Vista previa de PDF",
 "SSL 安全校验": "Verificación de seguridad SSL",
 "Chrome下载路径": "Ruta de descargas de Chrome",
 "Firefox下载路径": "Ruta de descargas de Firefox",
 "Cookie及其他网站数据": "Cookies y otros datos de sitios web",
 "在线文档浏览设置": "Configuración de navegación de documentos en línea",
 "文件下载默认保存位置": "Ubicación predeterminada de descargas",
 "当前位置: ": "Ubicación actual: ",
 "选择文件夹": "Seleccionar carpeta",
 "安全和隐私": "Seguridad y privacidad",
 "清除浏览数据": "Borrar datos de navegación",
 "浏览记录": "Historial de navegación",
 "时间范围": "Rango de tiempo",
 "过去 1 小时": "Última hora",
 "过去 24 小时": "Últimas 24 horas",
 "过去 7 天": "Últimos 7 días",
 "过去 4 周": "Últimas 4 semanas",
 "全部": "Todo",
 "缓存的图片和文件": "Imágenes y archivos en caché",
 "清除数据": "Borrar datos",
 "清除历史记录。": "Borrar el historial.",
 "清除已下载文件列表，不影响已下载的文件。": "Borra la lista de descargas sin afectar los archivos ya descargados.",
 "您会从大多数网站退出。": "Cerrará sesión en la mayoría de los sitios web.",
 "文件格式关联": "Asociación de formatos de archivo",
 "组件管理": "Gestión de componentes",
 "选择字体": "Seleccionar fuente",
 "无选项": "Sin opciones",
 "请选择": "Seleccione",
 "释放了 ": "Se liberaron ",
 "需要系统和GPU硬件加速支持": "Requiere soporte del sistema y aceleración por hardware GPU",
 "设置": "Configuración",
 "自动备份同步": "Copia de seguridad automática",
 "首页隐藏最近访问文档记录": "Ocultar el historial de documentos recientes en la página principal",
 "退出时保存工作状态": "Guardar el estado de trabajo al salir",
 "记录当前打开的标签和编辑状态，下次启动时自动恢复": "Recuerda las pestañas abiertas y el estado de edición, restaurándolos al reiniciar",
 "允许加入多人编辑": "Permitir unirse a la edición colaborativa",
 "多人或多设备同时打开文字、表格文档时，加入多人实时编辑": "Al abrir documentos o tablas desde varios usuarios o dispositivos, unirse a la edición colaborativa en tiempo real",
 "多人编辑文档用金山文档打开": "Abrir documentos colaborativos con WPS",
 "始终用金山文档客户端打开多人编辑文档": "Abrir siempre los documentos colaborativos con el cliente WPS",
 "登录其他Windows设备时，该设置项状态将会在设备上同步": "Al iniciar sesión en otros dispositivos, el estado de esta opción se sincronizará",
 "快速了解多设备同步文档的好处": "Conozca las ventajas de sincronizar documentos entre dispositivos"
}